npvec/__init__.py
npvec-0.1.0.dist-info/LICENSE
npvec-0.1.0.dist-info/METADATA
npvec-0.1.0.dist-info/WHEEL
npvec-0.1.0.dist-info/top_level.txt
npvec-0.1.0.dist-info/RECORD
